pymonobank/__init__.py
pymonobank/core/__init__.py
pymonobank/core/api.py
pymonobank/core/invoice/__init__.py
pymonobank/core/invoice/invoice.py
pymonobank/core/invoice/schemas.py
pymonobank/core/merchant/__init__.py
pymonobank/core/merchant/merchant.py
pymonobank/request/__init__.py
pymonobank/request/exceptions.py
pymonobank/request/methods.py
pymonobank/schemas/__init__.py
pymonobank/schemas/base.py
pymonobank/utils/__init__.py
pymonobank/utils/currencies/__init__.py
pymonobank-1.0.4.dist-info/METADATA
pymonobank-1.0.4.dist-info/WHEEL
pymonobank-1.0.4.dist-info/RECORD
